PyFinancials-0.1.1.dist-info/METADATA
PyFinancials-0.1.1.dist-info/RECORD
PyFinancials-0.1.1.dist-info/WHEEL
PyFinancials-0.1.1.dist-info/top_level.txt
pyfinancials/__init__.py
pyfinancials/engine.py
