Metadata-Version: 2.1
Name: PyFinancials
Version: 0.1.1
Summary: A framework that builds fully-working, editable financial models in Excel so you don't have to.
Home-page: https://github.com/kmiller96/PyFinancials
Author: Kale Miller
Author-email: me@kalelewismiller.com
License: MIT
Platform: UNKNOWN
